test_report_diff/__init__.py
test_report_diff/cli.py
test_report_diff/formatters/__init__.py
test_report_diff/formatters/default_formatter.py
test_report_diff/formatters/triage_formatter.py
test_report_diff/models/__init__.py
test_report_diff/models/diff.py
test_report_diff/models/status.py
test_report_diff/models/suite_result.py
test_report_diff/models/test_result.py
test_report_diff/processors/__init__.py
test_report_diff/processors/cuke_json.py
test_report_diff-0.1.0.dist-info/AUTHORS.rst
test_report_diff-0.1.0.dist-info/LICENSE
test_report_diff-0.1.0.dist-info/METADATA
test_report_diff-0.1.0.dist-info/WHEEL
test_report_diff-0.1.0.dist-info/entry_points.txt
test_report_diff-0.1.0.dist-info/top_level.txt
test_report_diff-0.1.0.dist-info/RECORD
